flask_cloud_services/__init__.py
flask_cloud_services/config.py
flask_cloud_services/contract.py
flask_cloud_services/constants/__init__.py
flask_cloud_services/constants/responses.py
flask_cloud_services/provider/__init__.py
flask_cloud_services/provider/aws.py
flask_cloud_services/provider/factory.py
flask_cloud_services/services/__init__.py
flask_cloud_services/services/notifications.py
flask_cloud_services/services/storage.py
flask_cloud_services-0.0.7.dist-info/LICENSE.txt
flask_cloud_services-0.0.7.dist-info/METADATA
flask_cloud_services-0.0.7.dist-info/WHEEL
flask_cloud_services-0.0.7.dist-info/top_level.txt
flask_cloud_services-0.0.7.dist-info/RECORD
